[
  {
    "id": "saudi-arabia-uruguay",
    "teamA": {
      "name": "Saudi Arabia",
      "icon": "https://flagcdn.com/w80/sa.png"
    },
    "teamB": {
      "name": "Uruguay",
      "icon": "https://flagcdn.com/w80/uy.png"
    },
    "leagueName": "FIFA World Cup - Group H",
    "prediction": "DOUBLE CHANCE X2",
    "date": "2026-06-15",
    "confidence": "Very High",
    "safetyRating": 9,
    "reason": "Uruguay have superior squad quality, defensive structure and tournament experience; X2 protects against a cautious opening-game draw."
  }
]
